LICENSE.txt
MANIFEST.in
glibc.py
pep425tags.py
requirements.txt
setup.cfg
setup.py
version.py
pymagnitude/__init__.py
pymagnitude/converter.py
pymagnitude/converter_shared.py
pymagnitude.egg-info/PKG-INFO
pymagnitude.egg-info/SOURCES.txt
pymagnitude.egg-info/dependency_links.txt
pymagnitude.egg-info/top_level.txt
pymagnitude/req_wheels/.gitkeep
pymagnitude/third_party/__init__.py
pymagnitude/third_party/repoze_LICENSE.txt
pymagnitude/third_party/_apsw/.gitignore
pymagnitude/third_party/_apsw/LICENSE
pymagnitude/third_party/_apsw/MANIFEST.in
pymagnitude/third_party/_apsw/Makefile
pymagnitude/third_party/_apsw/README.rst
pymagnitude/third_party/_apsw/checksums
pymagnitude/third_party/_apsw/example-code.py
pymagnitude/third_party/_apsw/mingwsetup.bat
pymagnitude/third_party/_apsw/setup.cfg
pymagnitude/third_party/_apsw/setup.py
pymagnitude/third_party/_apsw/tests.py
pymagnitude/third_party/_apsw/doc/Makefile
pymagnitude/third_party/_apsw/doc/benchmarking.rst
pymagnitude/third_party/_apsw/doc/build.rst
pymagnitude/third_party/_apsw/doc/changes.rst
pymagnitude/third_party/_apsw/doc/conf.py
pymagnitude/third_party/_apsw/doc/copyright.rst
pymagnitude/third_party/_apsw/doc/dbapi.rst
pymagnitude/third_party/_apsw/doc/download.rst
pymagnitude/third_party/_apsw/doc/exceptions.rst
pymagnitude/third_party/_apsw/doc/execution.rst
pymagnitude/third_party/_apsw/doc/extensions.rst
pymagnitude/third_party/_apsw/doc/index.rst
pymagnitude/third_party/_apsw/doc/pysqlite.rst
pymagnitude/third_party/_apsw/doc/shell.rst
pymagnitude/third_party/_apsw/doc/tips.rst
pymagnitude/third_party/_apsw/doc/types.rst
pymagnitude/third_party/_apsw/doc/_templates/layout.html
pymagnitude/third_party/_apsw/src/apsw.c
pymagnitude/third_party/_apsw/src/apswbuffer.c
pymagnitude/third_party/_apsw/src/apswversion.h
pymagnitude/third_party/_apsw/src/backup.c
pymagnitude/third_party/_apsw/src/blob.c
pymagnitude/third_party/_apsw/src/connection.c
pymagnitude/third_party/_apsw/src/cursor.c
pymagnitude/third_party/_apsw/src/exceptions.c
pymagnitude/third_party/_apsw/src/pypycompat.c
pymagnitude/third_party/_apsw/src/pyutil.c
