Metadata-Version: 1.1
Name: pymagnitude
Version: 0.1.120
Summary: A fast, efficient universal vector embedding utility package.
Home-page: https://gitlab.com/Plasticity/magnitude
Author: Plasticity
Author-email: opensource@plasticity.ai
License: MIT
Keywords: pymagnitude,magnitude,plasticity,nlp,natural,language,processing,word,vector,embeddings,embedding,word2vec,gensim,alternative,machine,learning,annoy,index,approximate,nearest,neighbors
Platform: UNKNOWN
Classifier: Development Status :: 5 - Production/Stable
Classifier: Intended Audience :: Developers
Classifier: Topic :: Software Development :: Libraries :: Python Modules
Classifier: Topic :: Scientific/Engineering :: Artificial Intelligence
Classifier: Topic :: Text Processing :: Linguistic
Classifier: Operating System :: OS Independent
Classifier: License :: OSI Approved :: MIT License
Classifier: Programming Language :: Python :: 2.7
Classifier: Programming Language :: Python :: 3
Classifier: Programming Language :: Python :: 3.0
Classifier: Programming Language :: Python :: 3.7
